MANIFEST.in
README.md
setup.py
Flask_MDBootstrap.egg-info/PKG-INFO
Flask_MDBootstrap.egg-info/SOURCES.txt
Flask_MDBootstrap.egg-info/dependency_links.txt
Flask_MDBootstrap.egg-info/not-zip-safe
Flask_MDBootstrap.egg-info/requires.txt
Flask_MDBootstrap.egg-info/top_level.txt
flask_mdbootstrap/__init__.py
flask_mdbootstrap/static/MDB-Pro/css/bootstrap.css
flask_mdbootstrap/static/MDB-Pro/css/bootstrap.min.css
flask_mdbootstrap/static/MDB-Pro/css/mdb.css
flask_mdbootstrap/static/MDB-Pro/css/mdb.lite.css
flask_mdbootstrap/static/MDB-Pro/css/mdb.lite.min.css
flask_mdbootstrap/static/MDB-Pro/css/mdb.min.css
flask_mdbootstrap/static/MDB-Pro/css/style.css
flask_mdbootstrap/static/MDB-Pro/css/addons/datatables-select.min.css
flask_mdbootstrap/static/MDB-Pro/css/addons/datatables.min.css
flask_mdbootstrap/static/MDB-Pro/css/addons/directives.min.css
flask_mdbootstrap/static/MDB-Pro/css/addons/flag.min.css
flask_mdbootstrap/static/MDB-Pro/css/addons/jquery.zmd.hierarchical-display.min.css
flask_mdbootstrap/static/MDB-Pro/css/addons/rating.min.css
flask_mdbootstrap/static/MDB-Pro/css/addons-pro/cards-extended.min.css
flask_mdbootstrap/static/MDB-Pro/css/addons-pro/chat.min.css
flask_mdbootstrap/static/MDB-Pro/css/addons-pro/multi-range.min.css
flask_mdbootstrap/static/MDB-Pro/css/addons-pro/simple-charts.min.css
flask_mdbootstrap/static/MDB-Pro/css/addons-pro/steppers.min.css
flask_mdbootstrap/static/MDB-Pro/css/addons-pro/timeline.min.css
flask_mdbootstrap/static/MDB-Pro/css/modules/accordion-extended.min.css
flask_mdbootstrap/static/MDB-Pro/css/modules/animations-extended.min.css
flask_mdbootstrap/static/MDB-Pro/css/modules/charts.min.css
flask_mdbootstrap/static/MDB-Pro/css/modules/lightbox.min.css
flask_mdbootstrap/static/MDB-Pro/css/modules/megamenu.min.css
flask_mdbootstrap/static/MDB-Pro/css/modules/parallax.min.css
flask_mdbootstrap/static/MDB-Pro/img/flags.png
flask_mdbootstrap/static/MDB-Pro/img/mdb-favicon.ico
flask_mdbootstrap/static/MDB-Pro/img/sample.jpg
flask_mdbootstrap/static/MDB-Pro/img/lightbox/default-skin.png
flask_mdbootstrap/static/MDB-Pro/img/lightbox/default-skin.svg
flask_mdbootstrap/static/MDB-Pro/img/lightbox/preloader.gif
flask_mdbootstrap/static/MDB-Pro/img/overlays/01.png
