Metadata-Version: 2.1
Name: Flask-MDBootstrap
Version: 3.0.5
Summary: An extension that includes material design for bootstrap in your project, without any boilerplate code.
Home-page: https://github.com/shijl0925/Flask-MDBootstrap
Author: Jialiang Shi
Author-email: kevin09254930sjl@gmail.com
License: MIT
Platform: any
Classifier: Environment :: Web Environment
Classifier: Intended Audience :: Developers
Classifier: License :: OSI Approved :: BSD License
Classifier: Operating System :: OS Independent
Classifier: Programming Language :: Python :: 3
Classifier: Topic :: Software Development :: Libraries :: Python Modules
